ptspy/__init__.py
ptspy/constants.py
ptspy-0.0.3.dist-info/LICENSE
ptspy-0.0.3.dist-info/WHEEL
ptspy-0.0.3.dist-info/METADATA
ptspy-0.0.3.dist-info/RECORD
